claude_kiro/__init__.py
claude_kiro/cli/__init__.py
claude_kiro/cli/hooks.py
claude_kiro/cli/main.py
claude_kiro/cli/runner.py
claude_kiro/hooks/__init__.py
claude_kiro/hooks/_shared/__init__.py
claude_kiro/hooks/_shared/cache_manager.py
claude_kiro/hooks/_shared/session_tracker.py
claude_kiro/hooks/_shared/spec_parser.py
claude_kiro/hooks/post_file_ops_spec_context.py
claude_kiro/resources/__init__.py
claude_kiro/resources/templates/__init__.py
claude_kiro/resources/templates/claude_md.md
claude_kiro/resources/templates/commands/__init__.py
claude_kiro/resources/templates/commands/spec/__init__.py
claude_kiro/resources/templates/commands/spec/create.md
claude_kiro/resources/templates/commands/spec/implement.md
claude_kiro/resources/templates/commands/spec/review.md
claude_kiro/resources/templates/output_styles/__init__.py
claude_kiro/resources/templates/output_styles/spec_driven.md
claude_kiro-0.1.0.dist-info/WHEEL
claude_kiro-0.1.0.dist-info/entry_points.txt
claude_kiro-0.1.0.dist-info/METADATA
claude_kiro-0.1.0.dist-info/RECORD
