Metadata-Version: 2.3
Name: claude-kiro
Version: 0.1.0
Summary: Add your description here
Author: Fredrik Angelsen
Author-email: Fredrik Angelsen <fredrikangelsen@gmail.com>
Requires-Dist: click>=8.3.0
Requires-Python: >=3.12
